Workbook

Sheet Guide
A1: Business Plan Financial Model (Template)
A2: Use for Chapter Five of your KNEC entrepreneurship business plan. Three-year projection in Kenya shillings (KES).
A4: How to use
A5: 1. Go to the Inputs sheet. Type your own figures in the yellow cells.
A6: 2. The values currently shown are EXAMPLE values for a fictional business. Replace every one with your own price quotes, survey results and costs.
A7: 3. Statements and BreakEven calculate automatically. Do not type over black cells.
A8: 4. Copy the results into the tables in Chapter Five of your report.
A9: 5. On the Statements sheet, the balance check must show 0. If it does not, an input is missing.
A11: Colour code
A12: Blue = typed input. Black = formula. Yellow fill = cell for you to fill in.
A14: Simplifying assumptions (state these in your report)
A15: Sales volume and variable cost per unit are the same through the year. Stock is held at the start-up level.
... A20: Every number must come from your own evidence. Keep quotes and survey summaries in the appendices.

Sheet Inputs
A1: Inputs (type in yellow cells)
A2: EXAMPLE VALUES for a fictional business. Replace all of them with your own evidence.
A3: Business
A4: Business name | B4: Example Business
A5: Sales and variable costs
A6: Selling price per unit, Year 1 | B6: 150 | C6: KES
A7: Units sold per month, Year 1 | B7: 800 | C7: units
A8: Growth in units, Year 2 | B8: 0.1 | C8: from Year 1
A9: Growth in units, Year 3 | B9: 0.1 | C9: from Year 2
A10: Yearly price increase | B10: 0.05 | C10: per year
A11: Variable cost per unit (materials, packaging) | B11: 90 | C11: KES
A12: Fixed operating costs (per month)
A13: Rent | B13: 8000 | C13: KES per month
A14: Salaries and wages | B14: 15000 | C14: KES per month
A15: Utilities | B15: 3000 | C15: KES per month
A16: Marketing | B16: 2000 | C16: KES per month
A17: Licences and permits | B17: 500 | C17: KES per month
A18: Other fixed costs | B18: 1500 | C18: KES per month
A19: Start-up costs
A20: Equipment and machinery | B20: 120000 | C20: KES
A21: Initial stock | B21: 40000 | C21: KES
A22: Registration, deposits, other start-up costs | B22: 30000 | C22: KES
A23: Useful life of equipment | B23: 5 | C23: years
A24: Funding
A25: Owner's capital | B25: 150000 | C25: KES
A26: Loan received | B26: 100000 | C26: KES
A27: Loan interest rate | B27: 0.12 | C27: per year
A28: Loan term | B28: 3 | C28: years
A29: Tax
A30: Tax rate on profit (check KRA rules) | B30: 0 | C30: enter the rate that applies

Sheet Statements
A1: Projected financial statements (KES)
A2: All cells calculate from the Inputs sheet.
A4: Sales volume and price | B4: Year 1 | C4: Year 2 | D4: Year 3
A5: Units sold | B5: =Inputs!B7*12 -> 9600 | C5: =B5*(1+Inputs!B8) -> 10560 | D5: =C5*(1+Inputs!B9) -> 11616
A6: Price per unit (KES) | B6: =Inputs!B6 -> 150 | C6: =B6*(1+Inputs!B10) -> 157.5 | D6: =C6*(1+Inputs!B10) -> 165.375
A8: Income statement | B8: Year 1 | C8: Year 2 | D8: Year 3
A9: Sales | B9: =B5*B6 -> 1440000 | C9: =C5*C6 -> 1663200 | D9: =D5*D6 -> 1920996
A10: Cost of goods sold | B10: =B5*Inputs!B11 -> 864000 | C10: =C5*Inputs!B11 -> 950400 | D10: =D5*Inputs!B11 -> 1045440
A11: Gross profit | B11: =B9-B10 -> 576000 | C11: =C9-C10 -> 712800 | D11: =D9-D10 -> 875556
A12: Operating expenses (fixed) | B12: =SUM(Inputs!B13:B18)*12 -> 360000 | C12: =SUM(Inputs!B13:B18)*12 -> 360000 | D12: =SUM(Inputs!B13:B18)*12 -> 360000
A13: Depreciation | B13: =IFERROR(Inputs!B20/Inputs!B23,0) -> 24000 | C13: =IFERROR(Inputs!B20/Inputs!B23,0) -> 24000 | D13: =IFERROR(Inputs!B20/Inputs!B23,0) -> 24000
A14: Operating profit | B14: =B11-B12-B13 -> 192000 | C14: =C11-C12-C13 -> 328800 | D14: =D11-D12-D13 -> 491556
A15: Interest | B15: =B21*Inputs!B27 -> 12000 | C15: =C21*Inputs!B27 -> 8000 | D15: =D21*Inputs!B27 -> 4000
A16: Profit before tax | B16: =B14-B15 -> 180000 | C16: =C14-C15 -> 320800 | D16: =D14-D15 -> 487556
A17: Tax | B17: =MAX(0,B16*Inputs!B30) -> 0 | C17: =MAX(0,C16*Inputs!B30) -> 0 | D17: =MAX(0,D16*Inputs!B30) -> 0
A18: Net profit | B18: =B16-B17 -> 180000 | C18: =C16-C17 -> 320800 | D18: =D16-D17 -> 487556
A20: Loan schedule | B20: Year 1 | C20: Year 2 | D20: Year 3
A21: Opening loan balance | B21: =Inputs!B26 -> 100000 | C21: =B23 -> 66666.667 | D21: =C23 -> 33333.333
A22: Principal repaid | B22: =IF(1<=Inputs!B28,MIN(B21,Inputs!B26/Inputs!B28),0) -> 33333.333 | C22: =IF(2<=Inputs!B28,MIN(C21,Inputs!B26/Inputs!B28),0) -> 33333.333 | D22: =IF(3<=Inputs!B28,MIN(D21,Inputs!B26/Inputs!B28),0) -> 33333.333
A23: Closing loan balance | B23: =B21-B22 -> 66666.667 | C23: =C21-C22 -> 33333.333 | D23: =D21-D22 -> 0
A25: Cash flow | B25: Year 1 | C25: Year 2 | D25: Year 3
A26: Opening cash | B26: =Inputs!B25+Inputs!B26-Inputs!B20-Inputs!B21-Inputs!B22 -> 60000 | C26: =B30 -> 230666.67 | D26: =C30 -> 542133.33
A27: Loan balance (memo) | B27: =B21 -> 100000 | C27: =C21 -> 66666.667 | D27: =D21 -> 33333.333
A28: Cash from operations (net profit + depreciation) | B28: =B18+B13 -> 204000 | C28: =C18+C13 -> 344800 | D28: =D18+D13 -> 511556
A29: Loan principal repaid | B29: =-B22 -> -33333.333 | C29: =-C22 -> -33333.333 | D29: =-D22 -> -33333.333
A30: Closing cash | B30: =B26+B28+B29 -> 230666.67 | C30: =C26+C28+C29 -> 542133.33 | D30: =D26+D28+D29 -> 1020356
A32: Balance sheet (end of year) | B32: Year 1 | C32: Year 2 | D32: Year 3
A33: Cash | B33: =B30 -> 230666.67 | C33: =C30 -> 542133.33 | D33: =D30 -> 1020356
A34: Equipment (net of depreciation) | B34: =Inputs!B20-B13 -> 96000 | C34: =B34-C13 -> 72000 | D34: =C34-D13 -> 48000
A35: Stock and other start-up assets | B35: =Inputs!B21+Inputs!B22 -> 70000 | C35: =Inputs!B21+Inputs!B22 -> 70000 | D35: =Inputs!B21+Inputs!B22 -> 70000
A36: Total assets | B36: =SUM(B33:B35) -> 396666.67 | C36: =SUM(C33:C35) -> 684133.33 | D36: =SUM(D33:D35) -> 1138356
A37: Loan outstanding | B37: =B23 -> 66666.667 | C37: =C23 -> 33333.333 | D37: =D23 -> 0
A38: Owner's equity (capital + retained profit) | B38: =Inputs!B25+B18 -> 330000 | C38: =B38+C18 -> 650800 | D38: =C38+D18 -> 1138356
A39: Total liabilities and equity | B39: =B37+B38 -> 396666.67 | C39: =C37+C38 -> 684133.33 | D39: =D37+D38 -> 1138356
A40: Balance check (must be 0) | B40: =ROUND(B36-B39,2) -> 0 | C40: =ROUND(C36-C39,2) -> 0 | D40: =ROUND(D36-D39,2) -> 0

Sheet BreakEven
A1: Break-even analysis (Year 1)
A3: Selling price per unit (KES) | B3: =Statements!B6 -> 150
A4: Variable cost per unit (KES) | B4: =Inputs!B11 -> 90
A5: Contribution per unit (KES) | B5: =B3-B4 -> 60
A6: Annual fixed costs: operating expenses + depreciation + interest | B6: =Statements!B12+Statements!B13+Statements!B15 -> 396000
A7: Break-even units per year | B7: =IFERROR(B6/B5,"") -> 6600
A8: Break-even units per month | B8: =IFERROR(B7/12,"") -> 550
A9: Break-even sales (KES per year) | B9: =IFERROR(B7*B3,"") -> 990000
A10: Planned units per year | B10: =Statements!B5 -> 9600
A11: Margin of safety (units above break-even) | B11: =IFERROR(B10-B7,"") -> 3000
A12: Margin of safety (% of planned units) | B12: =IFERROR(B11/B10,"") -> 0.3125
A14: Break-even units = fixed costs / contribution per unit. If planned units are below break-even, the business makes a loss.
